[
  {
    "imageUrl": "/gallery/cakes/pavlova-min.jpg",
    "title": "Tort Pavlova",
    "desc": ["Cu fistic și zmeură, cântărește aprox. 1 kg"],
    "unit": "buc",
    "price": 160
  },
  {
    "imageUrl": "/gallery/cakes/tort-stil-snickers-min.jpg",
    "title": "Tort stil Snickers",
    "desc": [
      "- Blat cacao",
      "- Cremă de brânză",
      "- Inserție de arahide cu caramel",
      "- Cremă de ciocolată cu pralină",
      "- Biluțe crocante de caramel sărat"
    ],
    "min": 1.7,
    "unit": "kg",
    "price": 140
  },
  {
    "imageUrl": "/gallery/cakes/vanilla-fruit-min.jpg",
    "title": "Vanilla Fruit",
    "desc": [
      "- Blat alb cu merișoare",
      "- Cremă frișcă si mascarpone",
      "- Inserție jeleu fructe",
      "- Salsa fructe pădure",
      "- Inserție lemon curd"
    ],
    "min": 1.7,
    "unit": "kg",
    "price": 140
  },
  {
    "imageUrl": "/gallery/cakes/carrot-cake-caramel-min.jpg",
    "title": "Tort carrot cu caramel",
    "desc": [
      "- Blat umed de morcov cu scorțișoară si nuca",
      "- Cremă de brânză cu portocală",
      "- Inserție de caramel"
    ],
    "min": 1.5,
    "unit": "kg",
    "price": 130
  },
  {
    "imageUrl": "/gallery/cakes/carrot-cake-fructe-min.jpg",
    "title": "Tort carrot cu fructe",
    "desc": [
      "- Blat umed de morcov cu scorțișoară si nuca",
      "- Cremă de brânză cu fructe de pădure"
    ],
    "min": 1.5,
    "unit": "kg",
    "price": 130
  },
  {
    "imageUrl": "/gallery/cakes/medovik-min.jpg",
    "title": "Tort Medovik",
    "desc": [
      "- Foi pufoase cu miere",
      "- Cremă de smântână cu cardamon",
      "- Fructe de pădure"
    ],
    "min": 1,
    "unit": "kg",
    "price": 140
  },
  {
    "imageUrl": "/gallery/cakes/medovik-cifra-min.jpg",
    "title": "Tort cifră Medovik",
    "desc": [
      "- Foi pufoase cu miere",
      "- Cremă de smântână cu cardamon",
      "- Fructe de pădure"
    ],
    "min": 1,
    "unit": "kg",
    "price": 150
  },
  {
    "imageUrl": "/gallery/cakes/diplomat-min.jpg",
    "title": "Tort Elegant",
    "desc": [
      "- Blat pandișpan însiropat cu compot",
      "- Șarlotă de vanilie cu frișcă",
      "- Fructe (ananas si piersica)",
      "- Jeleu de căpșuni"
    ],
    "min": 1.6,
    "unit": "kg",
    "price": 130
  },
  {
    "imageUrl": "/gallery/cakes/tort-mac-min.jpg",
    "title": "Summer Cake",
    "desc": [
      "- Blat cu mac",
      "- Inserție lemon curd",
      "- Inserție jeleu căpșuni",
      "- Cremă de frișcă cu mascarpone"
    ],
    "min": 1.5,
    "unit": "kg",
    "price": 130
  },
  {
    "imageUrl": "/gallery/cakes/tortul-casei-min.jpg",
    "title": "Tortul casei",
    "desc": [
      "- Blat cacao însiropat",
      "- Cremă de ciocolată neagră cu mascarpone",
      "- Șarlotă de vanilie",
      "- Inserție jeleu de căpșuni",
      "- Fructe de pădure"
    ],
    "min": 1.6,
    "unit": "kg",
    "price": 130
  }
]
