[
  {
    "imageUrl": "/gallery/cookies/rulada-pavlova",
    "title": "Ruladă Pavlova",
    "desc": [
      "- Foi pufoase de bezea",
      "- Cremă de smântână și mascarpone",
      "- Inserție fructe de pădure",
      "cântărește aprox. 1 kg"
    ],
    "min": 0,
    "unit": "buc",
    "price": 160
  },
  {
    "imageUrl": "/gallery/cookies/mini-prajituri",
    "title": "Mini Prăjituri",
    "assortments": "Choux fistic și zmeură, Choux alune de pădure, Pavlova, Tarte ciocolată",
    "min": 0,
    "unit": "kg",
    "price": 170
  },
  {
    "imageUrl": "/gallery/cookies/medovik",
    "title": "Medovik",
    "desc": [
      "- Foi pufoase cu miere",
      "- Cremă de smântână cu cardamon",
      "- Inserție fructe de pădure sau caramel"
    ],
    "min": 0,
    "unit": "buc",
    "price": 21
  },
  {
    "imageUrl": "/gallery/cookies/pavlova",
    "title": "Pavlova",
    "desc": ["- Bezea crocantă", "- Cremă de mascarpone și fructe"],
    "min": 0.5,
    "unit": "kg",
    "price": 170
  }
]
